AST/AST.py
AST/AST_pb2.py
AST/Anonymous0.py
AST/Element.py
AST/Kind.py
AST/LanguageType.py
AST/Literal.py
AST/LiteralType.py
AST/Unit.py
AST/__init__.py
AST/__main__.py
AST/pbjson.py
AST-0.0.1.dist-info/DESCRIPTION.rst
AST-0.0.1.dist-info/METADATA
AST-0.0.1.dist-info/RECORD
AST-0.0.1.dist-info/WHEEL
AST-0.0.1.dist-info/entry_points.txt
AST-0.0.1.dist-info/metadata.json
AST-0.0.1.dist-info/top_level.txt
